hc_nlp/__init__.py
hc_nlp/constants.py
hc_nlp/errors.py
hc_nlp/io.py
hc_nlp/logging.py
hc_nlp/model_testing.py
hc_nlp/pipeline.py
hc_nlp/spacy_helpers.py
hc_nlp-0.3.8.dist-info/METADATA
hc_nlp-0.3.8.dist-info/WHEEL
hc_nlp-0.3.8.dist-info/top_level.txt
hc_nlp-0.3.8.dist-info/RECORD
