Metadata-Version: 2.1
Name: hc-nlp
Version: 0.3.8
Summary: Heritage Connector NLP
Home-page: https://github.com/TheScienceMuseum/heritage-connector-nlp
Author: Science Museum Group
License: UNKNOWN
Download-URL: https://github.com/TheScienceMuseum/heritage-connector-nlp/archive/v0.3.8.tar.gz
Platform: UNKNOWN
Classifier: Programming Language :: Python :: 3
Classifier: License :: OSI Approved :: MIT License
Classifier: Operating System :: OS Independent
Requires-Python: >=3.6
Requires-Dist: spacy (>=3.0.0)
Requires-Dist: spacy-transformers (>=1.0.1)
